beautyacc/__init__.py
beautyacc/core/__init__.py
beautyacc/core/archive.py
beautyacc/util/__init__.py
beautyacc/util/caching.py
beautyacc-0.2.0.dist-info/METADATA
beautyacc-0.2.0.dist-info/RECORD
beautyacc-0.2.0.dist-info/WHEEL
beautyacc-0.2.0.dist-info/top_level.txt
beautyacc-0.2.0.dist-info/zip-safe
