Metadata-Version: 2.1
Name: beautyacc
Version: 0.2.0
Summary: Python package to access the EPICS RDB Archiver
Home-page: https://github.com/pklaus/beautyacc
Author: Philipp Klaus
Author-email: klaus@physik.uni-frankfurt.de
License: UNKNOWN
Platform: UNKNOWN
Classifier: Development Status :: 4 - Beta
Classifier: Operating System :: OS Independent
Classifier: License :: OSI Approved :: GNU General Public License v3 or later (GPLv3+)
Classifier: Programming Language :: Python
Classifier: Programming Language :: Python :: 3
Classifier: Topic :: Scientific/Engineering :: Physics
Requires-Dist: psycopg2-binary
